tests/conftest.py
tests/test_flash.py
tests/test_tag_handlers.py
tt_flash/__init__.py
tt_flash/blackhole.py
tt_flash/boot_fs.py
tt_flash/chip.py
tt_flash/error.py
tt_flash/flash.py
tt_flash/main.py
tt_flash/utility.py
tt_flash/data/blackhole/fw_defines.yaml
tt_flash/data/grayskull/fw_defines.yaml
tt_flash/data/wormhole/fw_defines.yaml
tt_flash-3.6.0.dist-info/licenses/LICENSE
tt_flash-3.6.0.dist-info/licenses/LICENSE_understanding.txt
tt_flash-3.6.0.dist-info/METADATA
tt_flash-3.6.0.dist-info/WHEEL
tt_flash-3.6.0.dist-info/entry_points.txt
tt_flash-3.6.0.dist-info/top_level.txt
tt_flash-3.6.0.dist-info/RECORD
