Metadata-Version: 2.4
Name: tt-flash
Version: 3.6.0
Summary: Utility to flash firmware blobs to tt devices
Author-email: Daniel Rosen <drosen@tenstorrent.com>
Maintainer-email: Daniel Rosen <drosen@tenstorrent.com>
License: 
Project-URL: Homepage, http://tenstorrent.com
Project-URL: Bug Reports, https://github.com/tenstorrent/tt-flash/issues
Project-URL: Source, https://github.com/tenstorrent/tt-flash
Classifier: Development Status :: 4 - Beta
Classifier: Environment :: Console :: Curses
Classifier: License :: OSI Approved :: Apache Software License
Classifier: Programming Language :: Python :: 3
Classifier: Programming Language :: Python :: 3.10
Classifier: Programming Language :: Python :: 3.11
Classifier: Programming Language :: Python :: 3 :: Only
Requires-Python: >=3.10
License-File: LICENSE
License-File: LICENSE_understanding.txt
Requires-Dist: pyyaml==6.0.2
Requires-Dist: tt_tools_common~=1.5
Requires-Dist: pyluwen~=0.8.0
Requires-Dist: tabulate==0.9.0
Requires-Dist: tomli==2.0.1; python_version < "3.11"
Requires-Dist: importlib-metadata>=1.4.0; python_version < "3.8"
Requires-Dist: importlib-resources>=1.3.0; python_version < "3.9"
Provides-Extra: dev
Requires-Dist: black==24.10.0; python_version >= "3.9" and extra == "dev"
Requires-Dist: black==24.8.0; python_version == "3.8" and extra == "dev"
Requires-Dist: black==23.3.0; python_version == "3.7" and extra == "dev"
Dynamic: license-file
Dynamic: requires-python
